whatshow_phy_detect_bpic/BPIC.py
whatshow_phy_detect_bpic/__init__.py
whatshow_phy_detect_bpic-1.0.5.dist-info/METADATA
whatshow_phy_detect_bpic-1.0.5.dist-info/WHEEL
whatshow_phy_detect_bpic-1.0.5.dist-info/top_level.txt
whatshow_phy_detect_bpic-1.0.5.dist-info/RECORD
