Metadata-Version: 2.1
Name: whatshow-phy-detect-bpic
Version: 1.0.5
Requires-Dist: numpy (>=1.23.5)
